CHANGELOG.rst
LICENSE
MANIFEST.in
README.rst
setup.cfg
setup.py
django_pypuppetdb/__init__.py
django_pypuppetdb/django_authentication.py
django_pypuppetdb/tastypie_authentication.py
django_pypuppetdb/user_authentication.py
django_pypuppetdb.egg-info/PKG-INFO
django_pypuppetdb.egg-info/SOURCES.txt
django_pypuppetdb.egg-info/dependency_links.txt
django_pypuppetdb.egg-info/top_level.txt