Metadata-Version: 1.1
Name: django-pypuppetdb
Version: 0.2.0
Summary: Handles authorization for Django by using puppetdb users
Home-page: https://github.com/nedap/django-pypuppetdb
Author: Ronald van Zon
Author-email: rvzon84+django-pypuppetdb@gmail.com
License: Apache License 2.0
Keywords: puppet puppetdb django authorization tastypie
Platform: UNKNOWN
Classifier: Development Status :: 4 - Beta
Classifier: Intended Audience :: Developers
Classifier: Natural Language :: English
Classifier: License :: OSI Approved :: Apache Software License
Classifier: Operating System :: POSIX
Classifier: Programming Language :: Python :: 2
Classifier: Programming Language :: Python :: 2.7
Classifier: Programming Language :: Python :: 3
Classifier: Programming Language :: Python :: 3.3
Classifier: Topic :: Software Development :: Libraries
